sense_core/__init__.py
sense_core/cache_func.py
sense_core/config.py
sense_core/django.py
sense_core/email.py
sense_core/encrypt.py
sense_core/es.py
sense_core/log.py
sense_core/mq_api.py
sense_core/mq_decode.py
sense_core/multi_process.py
sense_core/multi_thread_auto.py
sense_core/mysql.py
sense_core/object_id.py
sense_core/queue.py
sense_core/queue0.py
sense_core/queue2.py
sense_core/redis.py
sense_core/send_ali_msg.py
sense_core/sqlalchemy.py
sense_core/url_uuid.py
sense_core/utils.py
sense_core/wechat.py
sense_core_plus-0.0.1.dist-info/METADATA
sense_core_plus-0.0.1.dist-info/WHEEL
sense_core_plus-0.0.1.dist-info/top_level.txt
sense_core_plus-0.0.1.dist-info/RECORD
